Metadata-Version: 2.1
Name: sol-stats
Version: 0.1
Summary: this is a package created by vinit to find stats from a list
